{
  "version": 1,
  "title": "夢十夜",
  "chapters": [
    {
      "index": 1,
      "file": "001_夢十夜.txt",
      "title": "ユメジュウヤ",
      "original_title": "夢十夜",
      "source": "item/xhtml/title.xhtml"
    },
    {
      "index": 2,
      "file": "002_第一夜.txt",
      "title": "ダイイチャ",
      "original_title": "第一夜",
      "source": "item/xhtml/0001.xhtml"
    },
    {
      "index": 3,
      "file": "003_第二夜.txt",
      "title": "ダイニヤ",
      "original_title": "第二夜",
      "source": "item/xhtml/0001.xhtml"
    },
    {
      "index": 4,
      "file": "004_第三夜.txt",
      "title": "ダイサンヤ",
      "original_title": "第三夜",
      "source": "item/xhtml/0001.xhtml"
    },
    {
      "index": 5,
      "file": "005_第四夜.txt",
      "title": "ダイヨンヤ",
      "original_title": "第四夜",
      "source": "item/xhtml/0001.xhtml"
    },
    {
      "index": 6,
      "file": "006_第五夜.txt",
      "title": "ダイゴヤ",
      "original_title": "第五夜",
      "source": "item/xhtml/0001.xhtml"
    },
    {
      "index": 7,
      "file": "007_第六夜.txt",
      "title": "ダイロッヤ",
      "original_title": "第六夜",
      "source": "item/xhtml/0001.xhtml"
    },
    {
      "index": 8,
      "file": "008_第七夜.txt",
      "title": "ダイシチャ",
      "original_title": "第七夜",
      "source": "item/xhtml/0001.xhtml"
    },
    {
      "index": 9,
      "file": "009_第八夜.txt",
      "title": "ダイハッヤ",
      "original_title": "第八夜",
      "source": "item/xhtml/0001.xhtml"
    },
    {
      "index": 10,
      "file": "010_第九夜.txt",
      "title": "ダイキュウヤ",
      "original_title": "第九夜",
      "source": "item/xhtml/0001.xhtml"
    },
    {
      "index": 11,
      "file": "011_第十夜.txt",
      "title": "ダイジッヤ",
      "original_title": "第十夜",
      "source": "item/xhtml/0001.xhtml"
    },
    {
      "index": 12,
      "file": "012_底本_「夏目漱石全集10巻」ちくま文庫、筑摩書房.txt",
      "title": "テイホン:「ナツメソウセキゼンシュウ10マキ」チクマブンコ、チクマショボウ",
      "original_title": "底本:「夏目漱石全集10巻」ちくま文庫、筑摩書房",
      "source": "item/xhtml/0002.xhtml"
    }
  ],
  "author": "夏目漱石",
  "cover": "cover.jpg",
  "epub": "[夏目漱石] 夢十夜.epub",
  "tts_defaults": {
    "speaker": 2,
    "speed": 1.0,
    "pitch": 0.0,
    "intonation": 1.0
  }
}